perfect_physics/__init__.py
perfect_physics/_circle.py
perfect_physics/_misc.py
perfect_physics/_physics.py
perfect_physics/_timeline.py
perfect_physics/_wall.py
perfect_physics/_world.py
perfect_physics/data/Electronic Button.mp3
perfect_physics/data/Flash Beep.mp3
perfect_physics/data/ball_ball.wav
perfect_physics/data/bumper.wav
perfect_physics/data/cc_time_solutions.sympy
perfect_physics/data/cc_velocity_solution.sympy
perfect_physics/data/cw_time_solutions.sympy
perfect_physics/data/cw_velocity_limits.sympy
perfect_physics/data/instant_speed.sympy
perfect_physics/data/instant_speed_wall.sympy
perfect_physics/data/reverse.wav
perfect_physics/data/stick_cue.wav
perfect_physics/tests/__init__.py
perfect_physics/tests/test_perfect_physics.py
perfect_physics-0.1.9.dist-info/METADATA
perfect_physics-0.1.9.dist-info/WHEEL
perfect_physics-0.1.9.dist-info/top_level.txt
perfect_physics-0.1.9.dist-info/RECORD
