Metadata-Version: 2.1
Name: perfect-physics
Version: 0.1.9
Summary: Perfect Physics
Home-page: https://towardsdatascience.com/perfect-infinite-precision-game-physics-in-python-part-1-698211c08d95
Author: Carl Kadie
License: MIT or Apache-2.0
Requires-Dist: sympy
Requires-Dist: numpy
Requires-Dist: matplotlib
